rasa_integration_testing/__init__.py
rasa_integration_testing/__main__.py
rasa_integration_testing/application.py
rasa_integration_testing/cli.py
rasa_integration_testing/common.py
rasa_integration_testing/comparator.py
rasa_integration_testing/configuration.py
rasa_integration_testing/helper.py
rasa_integration_testing/identifier.py
rasa_integration_testing/interaction.py
rasa_integration_testing/logging_provider.py
rasa_integration_testing/protocol.py
rasa_integration_testing/runner.py
rasa_integration_testing/scenario.py
rasa_integration_testing/test_writer.py
rasa_integration_testing-0.1.3.dist-info/LICENSE
rasa_integration_testing-0.1.3.dist-info/WHEEL
rasa_integration_testing-0.1.3.dist-info/METADATA
rasa_integration_testing-0.1.3.dist-info/RECORD
